Workbook
Name JR_PAGE_ANCHOR_0_1: [1]Ventas!#REF!
Name Slicer_Mes: #N/A
Name Slicer_Nombre: #N/A

Sheet Sheet2
A1: Utilidad | B1: (Multiple Items)
A3: Row Labels | B3: Sum of Ventas totales | C3: Sum of Ventas totales2 | D3: Sum of Tickets | E3: Sum of Cost | F3: Sum of % de utilidad
A4: Jan | B4: 123177 | C4: 0.01526863 | D4: 1216 | E4: 56299 | F4: 0.54294227
A5: Feb | B5: 104939 | C5: 0.013007905 | D5: 971 | E5: 45784 | F5: 0.56370844
A6: Mar | B6: 94561 | C6: 0.011721481 | D6: 883 | E6: 38436 | F6: 0.59353222
A7: Apr | B7: 115651 | C7: 0.014335731 | D7: 1066 | E7: 46674 | F7: 0.59642372
A8: May | B8: 7628997 | C8: 0.94566625 | D8: 1132 | E8: -184872902 | F8: 25.232924
A9: Grand Total | B9: 8067325 | C9: 1 | D9: 5268 | E9: -184685709 | F9: 23.893054

Sheet Income Statement
A3: Ingreso ventas | B3: =SUM(Ventas!D2:D91) -> 355262 | D3: Ingreso ventas | E3: 174638
A4: Costo ventas | B4: =B3-SUM(Ventas!H2:H91) -> 171284 | D4: Costo ventas | E4: =E3*F4/100 -> 84198.972 | F4: =B4/B3*100 -> 48.213431
A5: Utilidad bruta | B5: =B3-B4 -> 183978 | D5: Utilidad bruta | E5: =E3-E4 -> 90439.028
A8: Renta | B8: =SUM('Gastos mensuales'!B2:D2) -> 27820 | D8: Renta | E8: =SUM('Gastos mensuales'!B2:D2) -> 27820
A9: Etiquetas | B9: =SUM('Gastos mensuales'!B3:D3) -> 4733 | D9: Etiquetas | E9: =SUM('Gastos mensuales'!B3:D3) -> 4733
A10: Internet | B10: =SUM('Gastos mensuales'!B4:D4) -> 1650 | D10: Internet | E10: =SUM('Gastos mensuales'!B4:D4) -> 1650
A11: Flete pedido | B11: =SUM('Gastos mensuales'!B5:D5) -> 7357 | D11: Flete pedido | E11: =SUM('Gastos mensuales'!B5:D5) -> 7357
A12: Redes sociales | B12: =SUM('Gastos mensuales'!B6:D6) -> 5000 | D12: Redes sociales | E12: =SUM('Gastos mensuales'!B6:D6) -> 5000
A13: Sistema | B13: =SUM('Gastos mensuales'!B7:D7) -> 660 | D13: Sistema | E13: =SUM('Gastos mensuales'!B7:D7) -> 660
A14: Sueldos | B14: =SUM('Gastos mensuales'!B8:D8) -> 41910 | D14: Sueldos | E14: =SUM('Gastos mensuales'!B8:D8) -> 41910
A15: Otros gastos | B15: =SUM('Gastos mensuales'!B9:D9) -> 748 | D15: Otros gastos | E15: =SUM('Gastos mensuales'!B9:D9) -> 748
A16: Mantenimiento | B16: =SUM('Gastos mensuales'!B10:D10) -> 561 | D16: Mantenimiento | E16: =SUM('Gastos mensuales'!B10:D10) -> 561
A17: Gastos operativos | B17: =SUM(B8:B16) -> 90439 | D17: Gastos operativos | E17: =SUM(E8:E16) -> 90439
A18: Utilidad operativa | B18: =B5-B17 -> 93539 | D18: Utilidad operativa | E18: =E5-E17 -> 0.027996239
A21: Utilidad neta | B21: =B18 -> 93539 | D21: Utilidad neta | E21: =E18 -> 0.027996239
A22: Margen de contribucion | B22: =B5/B3 -> 0.51786569 | D22: Margen de contribucion | E22: =E5/E3 -> 0.51786569
A23: Punto de equlibrio | B23: =B17/B22 -> 174637.95 | D23: Punto de equlibrio | E23: =E17/E22 -> 174637.95

Sheet DashBoard
A1: Resumen de ventas del año
A19: Resumen de ventas del mes
B22: Mes | C22: Mayo
B24: Ventas mensuales | C24: =D48 -> 133186
B25: Costo | C25: =I48 -> 54487
B26: Utilidad | C26: =H48 -> 78699
B27: Margen contribucion | C27: =J48 -> 0.40910456
D38: 1 | E38: 2 | F38: 3 | G38: 4 | H38: 5 | I38: 6 | J38: 7 | K38: 8 | L38: 9 | M38: 10 | N38: 11 | O38: 12
B39: Mes | C39: Número de mes | D39: Ventas totales | E39: Ventas efectivo | F39: Ventas tarjeta | G39: Ventas transferencia | H39: Utilidad | I39: Costo de venta | J39: margen contribución | K39: Tickets | L39: Tienda 1 | M39: Tienda 2 | N39: Tienda 3 | O39: Gastos
B40: Enero | C40: 1 | D40: =SUMIF(Ventas!$B:$B,DashBoard!$C40,Ventas!D:D) -> 123177 | E40: =SUMIF(Ventas!$B:$B,DashBoard!$C40,Ventas!E:E) -> 106378 | F40: =SUMIF(Ventas!$B:$B,DashBoard!$C40,Ventas!F:F) -> 11656 | G40: =SUMIF(Ventas!$B:$B,DashBoard!$C40,Ventas!G:G) -> 5132 | H40: =SUMIF(Ventas!$B:$B,DashBoard!$C40,Ventas!H:H) -> 66878 | I40: =D40-H40 -> 56299 | J40: =I40/D40 -> 0.45705773 | K40: =SUMIF(Ventas!$B:$B,DashBoard!$C40,Ventas!I:I) -> 1216 | L40: =INDEX('Ventas x tienda'!$D$2:$F$6,MATCH(DashBoard!$C40,'Ventas x tienda'!$A$2:$A$6,0),MATCH(DashBoard!L$39,'Ventas x tienda'!$D$1:$F$1,0)) -> 45580 | M40: =INDEX('Ventas x tienda'!$D$2:$F$6,MATCH(DashBoard!$C40,'Ventas x tienda'!$A$2:$A$6,0),MATCH(DashBoard!M$39,'Ventas x tienda'!$D$1:$F$1,0)) -> 34493 | N40: =INDEX('Ventas x tienda'!$D$2:$F$6,MATCH(DashBoard!$C40,'Ventas x tienda'!$A$2:$A$6,0),MATCH(DashBoard!N$39,'Ventas x tienda'!$D$1:$F$1,0)) -> 43116 | O40: =DSUM(Table2[#All],DashBoard!$B40,Table2[[#All],[Mes]]) -> 28156
B41: Febrero | C41: 2 | D41: =SUMIF(Ventas!$B:$B,DashBoard!$C41,Ventas!D:D) -> 110673 | E41: =SUMIF(Ventas!$B:$B,DashBoard!$C41,Ventas!E:E) -> 93410 | F41: =SUMIF(Ventas!$B:$B,DashBoard!$C41,Ventas!F:F) -> 17252 | G41: =SUMIF(Ventas!$B:$B,DashBoard!$C41,Ventas!G:G) -> 0 | H41: =SUMIF(Ventas!$B:$B,DashBoard!$C41,Ventas!H:H) -> 59979 | I41: =D41-H41 -> 50694 | J41: =I41/D41 -> 0.4580521 | K41: =SUMIF(Ventas!$B:$B,DashBoard!$C41,Ventas!I:I) -> 1025 | L41: =INDEX('Ventas x tienda'!$D$2:$F$6,MATCH(DashBoard!$C41,'Ventas x tienda'!$A$2:$A$6,0),MATCH(DashBoard!L$39,'Ventas x tienda'!$D$1:$F$1,0)) -> 41884 | M41: =INDEX('Ventas x tienda'!$D$2:$F$6,MATCH(DashBoard!$C41,'Ventas x tienda'!$A$2:$A$6,0),MATCH(DashBoard!M$39,'Ventas x tienda'!$D$1:$F$1,0)) -> 35725 | N41: =INDEX('Ventas x tienda'!$D$2:$F$6,MATCH(DashBoard!$C41,'Ventas x tienda'!$A$2:$A$6,0),MATCH(DashBoard!N$39,'Ventas x tienda'!$D$1:$F$1,0)) -> 33078 | O41: =DSUM(Table2[#All],DashBoard!$B41,Table2[[#All],[Mes]]) -> 28564
B42: Marzo | C42: 3 | D42: =SUMIF(Ventas!$B:$B,DashBoard!$C42,Ventas!D:D) -> 121412 | E42: =SUMIF(Ventas!$B:$B,DashBoard!$C42,Ventas!E:E) -> 103157 | F42: =SUMIF(Ventas!$B:$B,DashBoard!$C42,Ventas!F:F) -> 18070 | G42: =SUMIF(Ventas!$B:$B,DashBoard!$C42,Ventas!G:G) -> 175 | H42: =SUMIF(Ventas!$B:$B,DashBoard!$C42,Ventas!H:H) -> 57121 | I42: =D42-H42 -> 64291 | J42: =I42/D42 -> 0.52952756 | K42: =SUMIF(Ventas!$B:$B,DashBoard!$C42,Ventas!I:I) -> 1124 | L42: =INDEX('Ventas x tienda'!$D$2:$F$6,MATCH(DashBoard!$C42,'Ventas x tienda'!$A$2:$A$6,0),MATCH(DashBoard!L$39,'Ventas x tienda'!$D$1:$F$1,0)) -> 44348 | M42: =INDEX('Ventas x tienda'!$D$2:$F$6,MATCH(DashBoard!$C42,'Ventas x tienda'!$A$2:$A$6,0),MATCH(DashBoard!M$39,'Ventas x tienda'!$D$1:$F$1,0)) -> 36957 | N42: =INDEX('Ventas x tienda'!$D$2:$F$6,MATCH(DashBoard!$C42,'Ventas x tienda'!$A$2:$A$6,0),MATCH(DashBoard!N$39,'Ventas x tienda'!$D$1:$F$1,0)) -> 40121 | O42: =DSUM(Table2[#All],DashBoard!$B42,Table2[[#All],[Mes]]) -> 33719
B43: Abril | C43: 4 | D43: =SUMIF(Ventas!$B:$B,DashBoard!$C43,Ventas!D:D) -> 118542 | E43: =SUMIF(Ventas!$B:$B,DashBoard!$C43,Ventas!E:E) -> 104113 | F43: =SUMIF(Ventas!$B:$B,DashBoard!$C43,Ventas!F:F) -> 14415 | G43: =SUMIF(Ventas!$B:$B,DashBoard!$C43,Ventas!G:G) -> 0 | H43: =SUMIF(Ventas!$B:$B,DashBoard!$C43,Ventas!H:H) -> 70708 | I43: =D43-H43 -> 47834 | J43: =I43/D43 -> 0.40351943 | K43: =SUMIF(Ventas!$B:$B,DashBoard!$C43,Ventas!I:I) -> 1100 | L43: =INDEX('Ventas x tienda'!$D$2:$F$6,MATCH(DashBoard!$C43,'Ventas x tienda'!$A$2:$A$6,0),MATCH(DashBoard!L$39,'Ventas x tienda'!$D$1:$F$1,0)) -> 43116 | M43: =INDEX('Ventas x tienda'!$D$2:$F$6,MATCH(DashBoard!$C43,'Ventas x tienda'!$A$2:$A$6,0),MATCH(DashBoard!M$39,'Ventas x tienda'!$D$1:$F$1,0)) -> 36957 | N43: =INDEX('Ventas x tienda'!$D$2:$F$6,MATCH(DashBoard!$C43,'Ventas x tienda'!$A$2:$A$6,0),MATCH(DashBoard!N$39,'Ventas x tienda'!$D$1:$F$1,0)) -> 38483 | O43: =DSUM(Table2[#All],DashBoard!$B43,Table2[[#All],[Mes]]) -> 33307
B44: Mayo | C44: 5 | D44: =SUMIF(Ventas!$B:$B,DashBoard!$C44,Ventas!D:D) -> 133186 | E44: =SUMIF(Ventas!$B:$B,DashBoard!$C44,Ventas!E:E) -> 110865 | F44: =SUMIF(Ventas!$B:$B,DashBoard!$C44,Ventas!F:F) -> 1020364 | G44: =SUMIF(Ventas!$B:$B,DashBoard!$C44,Ventas!G:G) -> 2147 | H44: =SUMIF(Ventas!$B:$B,DashBoard!$C44,Ventas!H:H) -> 78699 | I44: =D44-H44 -> 54487 | J44: =I44/D44 -> 0.40910456 | K44: =SUMIF(Ventas!$B:$B,DashBoard!$C44,Ventas!I:I) -> 1132 | L44: =INDEX('Ventas x tienda'!$D$2:$F$6,MATCH(DashBoard!$C44,'Ventas x tienda'!$A$2:$A$6,0),MATCH(DashBoard!L$39,'Ventas x tienda'!$D$1:$F$1,0)) -> 43116 | M44: =INDEX('Ventas x tienda'!$D$2:$F$6,MATCH(DashBoard!$C44,'Ventas x tienda'!$A$2:$A$6,0),MATCH(DashBoard!M$39,'Ventas x tienda'!$D$1:$F$1,0)) -> 34493 | N44: =INDEX('Ventas x tienda'!$D$2:$F$6,MATCH(DashBoard!$C44,'Ventas x tienda'!$A$2:$A$6,0),MATCH(DashBoard!N$39,'Ventas x tienda'!$D$1:$F$1,0)) -> 48092 | O44: =DSUM(Table2[#All],DashBoard!$B44,Table2[[#All],[Mes]]) -> 29004
B45: Total | D45: =SUM(D40:D44) -> 606990 | E45: =SUM(E40:E44) -> 517923 | F45: =SUM(F40:F44) -> 1081757 | G45: =SUM(G40:G44) -> 7454 | H45: =SUM(H40:H44) -> 333385 | I45: =SUM(I40:I44) -> 273605 | J45: =I45/D45 -> 0.45075701 | K45: =SUM(K40:K44) -> 5597 | L45: =SUM(L40:L44) -> 218044 | M45: =SUM(M40:M44) -> 178625 | N45: =SUM(N40:N44) -> 202890 | O45: =SUM(O40:O44) -> 152750
B48: =C22 -> Mayo | C48: =VLOOKUP(B48,$B$40:$C$44,2,FALSE) -> 5 | D48: {=INDEX($D$40:$O$44,$C$48,D$38)} -> 133186 | E48: {=INDEX($D$40:$O$44,$C$48,E$38)} -> 110865 | F48: {=INDEX($D$40:$O$44,$C$48,F$38)} -> 1020364 | G48: {=INDEX($D$40:$O$44,$C$48,G$38)} -> 2147 | H48: {=INDEX($D$40:$O$44,$C$48,H$38)} -> 78699 | I48: {=INDEX($D$40:$O$44,$C$48,I$38)} -> 54487 | J48: {=INDEX($D$40:$O$44,$C$48,J$38)} -> 0.40910456 | K48: {=INDEX($D$40:$O$44,$C$48,K$38)} -> 1132 | ... O48: {=INDEX($D$40:$O$44,$C$48,O$38)} -> 29004

Sheet Ventas x tienda
A1: Mes | B1: Año | C1: Total | D1: Tienda 1 | E1: Tienda 2 | F1: Tienda 3
A2: 1 | B2: 2022 | C2: 123191 | D2: 45580 | E2: 34493 | F2: 43116
A3: 2 | B3: 2022 | C3: 110688 | D3: 41884 | E3: 35725 | F3: 33078
A4: 3 | B4: 2022 | C4: 121427 | D4: 44348 | E4: 36957 | F4: 40121
A5: 4 | B5: 2022 | C5: 118557 | D5: 43116 | E5: 36957 | F5: 38483
A6: 5 | B6: 2022 | C6: 133205 | D6: 43116 | E6: 34493 | F6: 48092

Sheet Ventas
A1: Fecha | B1: Mes | C1: Dia | D1: Ventas totales | E1: Ventas efectivo | F1: Ventas tarjeta | G1: Ventas transferencia | H1: Utilidad | I1: Tickets | M1: Mes | N1: Dia | O1: Año
A2: 44562 | B2: =MONTH(A2) -> 1 | C2: =WEEKDAY(Table3[[#This Row],[Fecha]]) -> 7 | D2: 0 | E2: 0 | F2: 0 | G2: 0 | H2: 0 | I2: 0 | K2: January | L2: Sunday | M2: =MATCH(K2,M14:M25,0) -> 1 | N2: =MATCH(L2,L19:L25,0) -> 7
A3: 44563 | B3: =MONTH(A3) -> 1 | C3: =WEEKDAY(Table3[[#This Row],[Fecha]]) -> 1 | D3: 3574 | E3: 3459 | F3: 114 | G3: 0 | H3: 1908 | I3: 25 | M3: Ventas totales por mes | N3: Ventas totales por dia
A4: 44564 | B4: =MONTH(A4) -> 1 | C4: =WEEKDAY(Table3[[#This Row],[Fecha]]) -> 2 | D4: 4942 | E4: 4942 | F4: 0 | G4: 0 | H4: 2553 | I4: 47 | M4: =SUMIF(B:B,$M$2,D:D) -> 123177 | N4: =SUMIFS(D:D,B:B,$M$2,C:C,$N$2) -> 21358
A5: 44565 | B5: =MONTH(A5) -> 1 | C5: =WEEKDAY(Table3[[#This Row],[Fecha]]) -> 3 | D5: 5551 | E5: 5108 | F5: 443 | G5: 0 | H5: 2692 | I5: 55
A6: 44566 | B6: =MONTH(A6) -> 1 | C6: =WEEKDAY(Table3[[#This Row],[Fecha]]) -> 4 | D6: 6001 | E6: 5876 | F6: 125 | G6: 0 | H6: 3018 | I6: 58
A7: 44567 | B7: =MONTH(A7) -> 1 | C7: =WEEKDAY(Table3[[#This Row],[Fecha]]) -> 5 | D7: 4118 | E7: 3962 | F7: 156 | G7: 0 | H7: 2053 | I7: 50
A8: 44568 | B8: =MONTH(A8) -> 1 | C8: =WEEKDAY(Table3[[#This Row],[Fecha]]) -> 6 | D8: 5649 | E8: 4933 | F8: 716 | G8: 0 | H8: 2779 | I8: 59
A9: 44569 | B9: =MONTH(A9) -> 1 | C9: =WEEKDAY(Table3[[#This Row],[Fecha]]) -> 7 | D9: 5302 | E9: 4907 | F9: 394 | G9: 0 | H9: 2587 | I9: 58
A10: 44570 | B10: =MONTH(A10) -> 1 | C10: =WEEKDAY(Table3[[#This Row],[Fecha]]) -> 1 | D10: 3478 | E10: 1596 | F10: 1881 | G10: 0 | H10: 1746 | I10: 32
A11: 44571 | B11: =MONTH(A11) -> 1 | C11: =WEEKDAY(Table3[[#This Row],[Fecha]]) -> 2 | D11: 7573 | E11: 2347 | F11: 94 | G11: 5132 | H11: 3802 | I11: 32
A12: 44572 | B12: =MONTH(A12) -> 1 | C12: =WEEKDAY(Table3[[#This Row],[Fecha]]) -> 3 | D12: 4226 | E12: 3692 | F12: 533 | G12: 0 | H12: 2411 | I12: 46
A13: 44573 | B13: =MONTH(A13) -> 1 | C13: =WEEKDAY(Table3[[#This Row],[Fecha]]) -> 4 | D13: 4172 | E13: 4172 | F13: 0 | G13: 0 | H13: 2291 | I13: 48
A14: 44574 | B14: =MONTH(A14) -> 1 | C14: =WEEKDAY(Table3[[#This Row],[Fecha]]) -> 5 | D14: 3580 | E14: 3217 | F14: 363 | G14: 0 | H14: 2032 | I14: 39 | M14: January
A15: 44575 | B15: =MONTH(A15) -> 1 | C15: =WEEKDAY(Table3[[#This Row],[Fecha]]) -> 6 | D15: 3503 | E15: 2831 | F15: 671 | G15: 0 | H15: 1996 | I15: 33 | M15: February
A16: 44576 | B16: =MONTH(A16) -> 1 | C16: =WEEKDAY(Table3[[#This Row],[Fecha]]) -> 7 | D16: 6727 | E16: 5752 | F16: 975 | G16: 0 | H16: 3750 | I16: 48 | M16: March
A17: 44577 | B17: =MONTH(A17) -> 1 | C17: =WEEKDAY(Table3[[#This Row],[Fecha]]) -> 1 | D17: 3620 | E17: 3216 | F17: 403 | G17: 0 | H17: 2127 | I17: 28 | M17: April
A18: 44578 | B18: =MONTH(A18) -> 1 | C18: =WEEKDAY(Table3[[#This Row],[Fecha]]) -> 2 | D18: 3178 | E18: 3154 | F18: 24 | G18: 0 | H18: 1826 | I18: 34 | M18: May
A19: 44579 | B19: =MONTH(A19) -> 1 | C19: =WEEKDAY(Table3[[#This Row],[Fecha]]) -> 3 | D19: 3765 | E19: 3388 | F19: 377 | G19: 0 | H19: 2082 | I19: 40 | L19: Monday | M19: June
A20: 44580 | B20: =MONTH(A20) -> 1 | C20: =WEEKDAY(Table3[[#This Row],[Fecha]]) -> 4 | D20: 3966 | E20: 3605 | F20: 361 | G20: 0 | H20: 2216 | I20: 53 | L20: Tuesday | M20: July
A21: 44581 | B21: =MONTH(A21) -> 1 | C21: =WEEKDAY(Table3[[#This Row],[Fecha]]) -> 5 | D21: 3706 | E21: 3706 | F21: 0 | G21: 0 | H21: 2076 | I21: 42 | L21: Wednesday | M21: August
A22: 44582 | B22: =MONTH(A22) -> 1 | C22: =WEEKDAY(Table3[[#This Row],[Fecha]]) -> 6 | D22: 2753 | E22: 2753 | F22: 0 | G22: 0 | H22: 1611 | I22: 35 | L22: Thursday | M22: September
A23: 44583 | B23: =MONTH(A23) -> 1 | C23: =WEEKDAY(Table3[[#This Row],[Fecha]]) -> 7 | D23: 6177 | E23: 4991 | F23: 1185 | G23: 0 | H23: 3505 | I23: 51 | L23: Friday | M23: October
A24: 44584 | B24: =MONTH(A24) -> 1 | C24: =WEEKDAY(Table3[[#This Row],[Fecha]]) -> 1 | D24: 2919 | E24: 2833 | F24: 85 | G24: 0 | H24: 1654 | I24: 26 | L24: Saturday | M24: November
A25: 44585 | B25: =MONTH(A25) -> 1 | C25: =WEEKDAY(Table3[[#This Row],[Fecha]]) -> 2 | D25: 3034 | E25: 2721 | F25: 313 | G25: 0 | H25: 1758 | I25: 31 | L25: Sunday | M25: December
A26: 44586 | B26: =MONTH(A26) -> 1 | C26: =WEEKDAY(Table3[[#This Row],[Fecha]]) -> 3 | D26: 2491 | E26: 2365 | F26: 125 | G26: 0 | H26: 1430 | I26: 34
A27: 44587 | B27: =MONTH(A27) -> 1 | C27: =WEEKDAY(Table3[[#This Row],[Fecha]]) -> 4 | D27: 1881 | E27: 1714 | F27: 167 | G27: 0 | H27: 1141 | I27: 24
A28: 44588 | B28: =MONTH(A28) -> 1 | C28: =WEEKDAY(Table3[[#This Row],[Fecha]]) -> 5 | D28: 2533 | E28: 1714 | F28: 818 | G28: 0 | H28: 1442 | I28: 34
A29: 44589 | B29: =MONTH(A29) -> 1 | C29: =WEEKDAY(Table3[[#This Row],[Fecha]]) -> 6 | D29: 4445 | E29: 4286 | F29: 159 | G29: 0 | H29: 2488 | I29: 45
A30: 44590 | B30: =MONTH(A30) -> 1 | C30: =WEEKDAY(Table3[[#This Row],[Fecha]]) -> 7 | D30: 3152 | E30: 2150 | F30: 1001 | G30: 0 | H30: 1844 | I30: 26
A31: 44591 | B31: =MONTH(A31) -> 1 | C31: =WEEKDAY(Table3[[#This Row],[Fecha]]) -> 1 | D31: 2940 | E31: 2819 | F31: 121 | G31: 0 | H31: 1669 | I31: 29
A32: 44592 | B32: =MONTH(A32) -> 1 | C32: =WEEKDAY(Table3[[#This Row],[Fecha]]) -> 2 | D32: 4221 | E32: 4169 | F32: 52 | G32: 0 | H32: 2391 | I32: 54
A33: 44593 | B33: =MONTH(A33) -> 2 | C33: =WEEKDAY(Table3[[#This Row],[Fecha]]) -> 3 | D33: 4717 | E33: 4360 | F33: 357 | G33: 0 | H33: 2616 | I33: 47
A34: 44594 | B34: =MONTH(A34) -> 2 | C34: =WEEKDAY(Table3[[#This Row],[Fecha]]) -> 4 | D34: 4845 | E34: 4845 | F34: 0 | G34: 0 | H34: 2699 | I34: 42
A35: 44595 | B35: =MONTH(A35) -> 2 | C35: =WEEKDAY(Table3[[#This Row],[Fecha]]) -> 5 | D35: 3418 | E35: 3305 | F35: 112 | G35: 0 | H35: 1962 | I35: 33
A36: 44596 | B36: =MONTH(A36) -> 2 | C36: =WEEKDAY(Table3[[#This Row],[Fecha]]) -> 6 | D36: 3483 | E36: 2786 | F36: 697 | G36: 0 | H36: 1975 | I36: 39
A37: 44597 | B37: =MONTH(A37) -> 2 | C37: =WEEKDAY(Table3[[#This Row],[Fecha]]) -> 7 | D37: 4180 | E37: 3462 | F37: 717 | G37: 0 | H37: 2371 | I37: 38
... A152: 44712 | B152: =MONTH(A152) -> 5 | C152: =WEEKDAY(Table3[[#This Row],[Fecha]]) -> 3 | D152: 2905 | E152: 2672 | F152: 235715 | G152: 0 | H152: 1605 | I152: 0

Sheet G Venta x vendedor
A1: Row Labels | B1: Sum of enero | C1: Sum of febrero
A2: JoseRomero | B2: 221743836 | C2: 232445724
A3: JuanLopez | B3: 283339346 | C3: 215842458
A4: MariaGonzález | B4: 147829224 | C4: 199239192
A5: RobertoMartinez | B5: 30797755 | C5: 204773614
A6: SandraBlanco | B6: 271020244 | C6: 254583412
A7: Junior Mosquera | B7: 103994 | C7: 43434545
A8: Grand Total | B8: 954834399 | C8: 1150318945

Sheet Ventas x vendedor
A1: Vendedor | B1: Rol | C1: Id | D1: Nombre | E1: enero | F1: febrero | G1: marzo | H1: abril | I1: mayo
A2: V-0001-JuanLopez | B2: V | C2: 1 | D2: JuanLopez | E2: 283339346 | F2: 215842458 | G2: 24285438 | H2: 225258699 | I2: 279732432
A3: V-0002-MariaGonzález | B3: V | C3: 2 | D3: MariaGonzález | E3: 147829224 | F3: 199239192 | G3: 267139818 | H3: 201547257 | I3: 26641184
A4: V-0003-SandraBlanco | B4: V | C4: 3 | D4: SandraBlanco | E4: 271020244 | F4: 254583412 | G4: 230711661 | H4: 23711442 | I4: 306373616
A5: V-0004-JoseRomero | B5: V | C5: 4 | D5: JoseRomero | E5: 221743836 | F5: 232445724 | G5: 206426223 | H5: 248970141 | I5: 253091248
A6: V-0005-RobertoMartinez | B6: V | C6: 5 | D6: RobertoMartinez | E6: 30797755 | F6: 204773614 | G6: 267139818 | H6: 272681583 | I6: 226450064
D7: Junior Mosquera | E7: 103994 | F7: 43434545 | G7: 5634 | H7: 34345 | I7: 656

Sheet Registro clientes
A1: Nombre Cliente | B1: Teléfono | C1: Fecha de compra | D1: Tienda | E1: Vendedor | F1: Requiere factura | G1: Forma de pago
C2: 45060 | D2: Tienda 2 | E2: V-0004-JoseRomero | F2: Si | G2: Ventas tarjeta

Sheet G Gastos mensuales
A1: Row Labels | B1: Sum of Enero | C1: Sum of Febrero | D1: Sum of Marzo
A2: Etiquetas | B2: 2336 | C2: 0 | D2: 2397
A3: Flete pedido | B3: 2433 | C3: 2684 | D3: 2240
A4: Internet | B4: 550 | C4: 550 | D4: 550
A5: Mantenimiento | B5: 152 | C5: 119 | D5: 290
A6: Otros gastos | B6: 305 | C6: 381 | D6: 62
A7: Redes sociales | B7: 0 | C7: 2500 | D7: 2500
A8: Renta | B8: 9280 | C8: 9280 | D8: 9260
A9: Sistema | B9: 0 | C9: 0 | D9: 660
A10: Sueldos | B10: 13100 | C10: 13050 | D10: 15760
A11: Grand Total | B11: 28156 | C11: 28564 | D11: 33719

Sheet Gastos mensuales
A1: Mes | B1: Enero | C1: Febrero | D1: Marzo | E1: Abril | F1: Mayo | G1: Junio
A2: Renta | B2: 9280 | C2: 9280 | D2: 9260 | E2: 9280 | F2: 9280 | G2: =SUM(B2:D2) -> 27820 | L2: Concepto | M2: mes | N2: Gasto
A3: Etiquetas | B3: 2336 | C3: 0 | D3: 2397 | E3: 2908.12 | F3: 3887.16 | G3: =SUM(B3:D3) -> 4733 | J3: =INDEX(Table2[#All],1,5) -> Abril | L3: Sistema | M3: Marzo | N3: =INDEX(Table2[[Enero]:[Junio]],MATCH(L3,Table2[Mes],0),MATCH(M3,Table2[[#Headers],[Enero]:[Junio]],0)) -> 660
A4: Internet | B4: 550 | C4: 550 | D4: 550 | E4: 550 | F4: 550 | G4: =SUM(B4:D4) -> 1650 | J4: =MATCH("Enero",Table2[[#Headers],[Enero]:[Junio]],0) -> 1
A5: Flete pedido | B5: 2433 | C5: 2684 | D5: 2240 | E5: 2628 | F5: 2623.5 | G5: =SUM(B5:D5) -> 7357
A6: Redes sociales | B6: 0 | C6: 2500 | D6: 2500 | E6: 2500 | F6: 2500 | G6: =SUM(B6:D6) -> 5000
A7: Sistema | B7: 0 | C7: 0 | D7: 660 | E7: 660.75 | F7: 660.75 | G7: =SUM(B7:D7) -> 660
A8: Sueldos | B8: 13100 | C8: 13050 | D8: 15760 | E8: 17432 | F8: 15620 | G8: =SUM(B8:D8) -> 41910
A9: Otros gastos | B9: 305 | C9: 381 | D9: 62 | E9: 818. | F9: 700 | G9: =SUM(B9:D9) -> 748
A10: Mantenimiento | B10: 152 | C10: 119 | D10: 290 | E10: 917 | F10: 354 | G10: =SUM(B10:D10) -> 561
J13: Enero
J14: Febrero
J15: Marzo
J16: Abril
J17: Mayo
J18: Junio
